quantization/__init__.py
quantization-0.0.1.dist-info/LICENSE
quantization-0.0.1.dist-info/METADATA
quantization-0.0.1.dist-info/WHEEL
quantization-0.0.1.dist-info/RECORD
